cabot/__init__.py
cabot/modules/__init__.py
cabot/modules/backend/__init__.py
cabot/modules/backend/DiscoBall/DiscoBall.py
cabot/modules/backend/DiscoBall/__init__.py
cabot_discoball-0.1.0.dist-info/LICENSE
cabot_discoball-0.1.0.dist-info/METADATA
cabot_discoball-0.1.0.dist-info/WHEEL
cabot_discoball-0.1.0.dist-info/top_level.txt
cabot_discoball-0.1.0.dist-info/RECORD
