Metadata-Version: 2.1
Name: cabot-discoball
Version: 0.1.0
Summary: The caBot Discoball Module.
Home-page: https://github.com/centennialarts/cabot-discoball
Author: Joseph Hanna
Author-email: josephhanna@centennialarts.com
License: MIT
Download-URL: https://github.com/centennialarts/cabot-discoball/archive/master.zip
Keywords: Chatbot,Discoball
Platform: UNKNOWN
Classifier: Development Status :: 2 - Pre-Alpha
Classifier: Intended Audience :: Developers
Classifier: Topic :: Communications :: Chat :: Internet Relay Chat
Classifier: License :: OSI Approved :: MIT License
Classifier: Programming Language :: Python :: 3
Requires-Dist: cabot-core
